wagtail_admin_modals/__init__.py
wagtail_admin_modals/apps.py
wagtail_admin_modals/panels.py
wagtail_admin_modals/registry.py
wagtail_admin_modals/views.py
wagtail_admin_modals/static/wagtail_admin_modals/css/modal-defaults.css
wagtail_admin_modals/static/wagtail_admin_modals/css/modal-tabs.css
wagtail_admin_modals/static/wagtail_admin_modals/js/modal-tabs.js
wagtail_admin_modals/static/wagtail_admin_modals/js/modal-workflow-wrapper.js
wagtail_admin_modals/templates/wagtail_admin_modals/base_modal.html
wagtail_admin_modals/templates/wagtail_admin_modals/base_modal_tabbed.html
wagtail_admin_modals/templates/wagtail_admin_modals/panels/button_panel.html
wagtail_admin_modals-0.3.0.dist-info/licenses/LICENSE
wagtail_admin_modals-0.3.0.dist-info/METADATA
wagtail_admin_modals-0.3.0.dist-info/WHEEL
wagtail_admin_modals-0.3.0.dist-info/top_level.txt
wagtail_admin_modals-0.3.0.dist-info/RECORD
