Metadata-Version: 2.4
Name: wagtail-admin-modals
Version: 0.3.0
Summary: Supports custom modal workflows for Wagtail admin
Author-email: "Nicholas Roy / FormuLearn B.V." <nicholas.roy@formulearn.org>
License: GPL-3.0-only
Project-URL: Homepage, https://github.com/FormuLearn/wagtail-admin-modals
Project-URL: Documentation, https://docs.formulearn.org/docs/projects/wagtail-admin-modals/
Requires-Python: >=3.10
License-File: LICENSE
Requires-Dist: Django>=5.1
Requires-Dist: wagtail>=6.2
Dynamic: license-file
